shnitsel/__init__.py
shnitsel/_accessors.py
shnitsel/_contracts.py
shnitsel/_generated_accessors.py
shnitsel/_state.py
shnitsel/bridges.py
shnitsel/rd.py
shnitsel/xarray.py
shnitsel/analyze/__init__.py
shnitsel/analyze/generic.py
shnitsel/analyze/hops.py
shnitsel/analyze/lda.py
shnitsel/analyze/pca.py
shnitsel/analyze/pls.py
shnitsel/analyze/populations.py
shnitsel/analyze/spectra.py
shnitsel/analyze/stats.py
shnitsel/clean/__init__.py
shnitsel/clean/common.py
shnitsel/clean/dispatch_plots.py
shnitsel/clean/filter_energy.py
shnitsel/clean/filter_geo.py
shnitsel/clean/filtration_class.py
shnitsel/cli/convert_to_shnitsel.py
shnitsel/cli/generate_datasheet.py
shnitsel/cli/merge_shnitsel_files.py
shnitsel/core/__init__.py
shnitsel/core/_api_info.py
shnitsel/core/feature_detection.py
shnitsel/core/typedefs.py
shnitsel/data/__init__.py
shnitsel/data/atom_helpers.py
shnitsel/data/charge_helpers.py
shnitsel/data/helpers.py
shnitsel/data/multi_indices.py
shnitsel/data/proxy_class.py
shnitsel/data/shnitsel_db_helpers.py
shnitsel/data/state_helpers.py
shnitsel/data/traj_combiner_methods.py
shnitsel/data/trajectory_grouping_params.py
shnitsel/data/trajectory_variable_description.py
shnitsel/data/xr_io_compatibility.py
shnitsel/data/xr_io_registry.py
shnitsel/data/dataset_containers/__init__.py
shnitsel/data/dataset_containers/data_series.py
shnitsel/data/dataset_containers/dataset_vis.py
shnitsel/data/dataset_containers/frames.py
shnitsel/data/dataset_containers/inter_state.py
shnitsel/data/dataset_containers/multi_layered.py
shnitsel/data/dataset_containers/multi_series.py
shnitsel/data/dataset_containers/multi_stacked.py
shnitsel/data/dataset_containers/per_state.py
shnitsel/data/dataset_containers/shared.py
shnitsel/data/dataset_containers/trajectory.py
shnitsel/data/dataset_containers/trajectory_collection.py
shnitsel/data/dataset_containers/xr_conversion.py
shnitsel/data/shnitsel_db/__init__.py
shnitsel/data/shnitsel_db/db_function_decorator.py
shnitsel_tools-2026.1.1.dist-info/licenses/LICENSE
shnitsel_tools-2026.1.1.dist-info/METADATA
shnitsel_tools-2026.1.1.dist-info/WHEEL
shnitsel_tools-2026.1.1.dist-info/entry_points.txt
shnitsel_tools-2026.1.1.dist-info/top_level.txt
shnitsel_tools-2026.1.1.dist-info/RECORD
