Metadata-Version: 2.4
Name: shnitsel-tools
Version: 2026.1.1
Summary: Collect, manage, process, analyse & visualize surface hopping data
Author-email: Theodor Everley Röhrkasten <theodor.roehrkasten@fau.de>, Kevin Höllring <kevin.hoellring@fau.de>, Carolin Müller <carolin.cpc.mueller@fau.de>
Classifier: Programming Language :: Python :: 3
Classifier: License :: OSI Approved :: MIT License
Classifier: Operating System :: OS Independent
Requires-Python: >=3.11
License-File: LICENSE
Requires-Dist: scipy>=1.16
Requires-Dist: matplotlib>=3.10
Requires-Dist: xarray>=2025.7.1
Requires-Dist: rdkit>=2025
Requires-Dist: ase>=3
Requires-Dist: numpy>=2.3
Requires-Dist: pandas>=2.2
Requires-Dist: h5netcdf>=1.7.0
Requires-Dist: scikit-learn>=1.5
Requires-Dist: jupyter>=1.0.0
Requires-Dist: py3dmol>=2.0.4
Requires-Dist: tqdm>=4.66.2
Requires-Dist: pyparsing>=3.2.5
Requires-Dist: svgpathtools>=1.7.2
Requires-Dist: fsspec
Requires-Dist: requests
Requires-Dist: aiohttp
Provides-Extra: vis
Requires-Dist: bokeh>=3.5; extra == "vis"
Requires-Dist: datashader; extra == "vis"
Requires-Dist: numba>=0.60; extra == "vis"
Requires-Dist: seaborn>=0.13.2; extra == "vis"
Requires-Dist: holoviews>=1.22.1; extra == "vis"
Provides-Extra: dev
Requires-Dist: pytest>=5.2; extra == "dev"
Requires-Dist: pytest-cov>=4.1.0; extra == "dev"
Requires-Dist: hypothesis>=6; extra == "dev"
Requires-Dist: tox>=4.10.0; extra == "dev"
Requires-Dist: tox-uv>=1.29.0; extra == "dev"
Requires-Dist: pre-commit>=2.20.0; extra == "dev"
Requires-Dist: ruff>=0.5.3; extra == "dev"
Requires-Dist: mypy>=1.9.0; extra == "dev"
Requires-Dist: pandas-stubs; extra == "dev"
Requires-Dist: scipy-stubs; extra == "dev"
Requires-Dist: types-tqdm; extra == "dev"
Requires-Dist: build; extra == "dev"
Requires-Dist: grayskull; extra == "dev"
Requires-Dist: sphinx==8.2.3; extra == "dev"
Requires-Dist: sphinx-autobuild; extra == "dev"
Requires-Dist: sphinx-autosummary-accessors; extra == "dev"
Requires-Dist: nbsphinx; extra == "dev"
Requires-Dist: sphinx-design; extra == "dev"
Requires-Dist: sphinx-autoapi; extra == "dev"
Requires-Dist: pydata-sphinx-theme; extra == "dev"
Dynamic: license-file
